jsonschema2shacl/__init__.py
jsonschema2shacl/__main__.py
jsonschema2shacl/constants.py
jsonschema2shacl/file_parser.py
jsonschema2shacl/json_schema_to_shacl.py
jsonschema2shacl/utils.py
jsonschema2shacl-0.2.dist-info/LICENSE
jsonschema2shacl-0.2.dist-info/METADATA
jsonschema2shacl-0.2.dist-info/WHEEL
jsonschema2shacl-0.2.dist-info/RECORD
